odoo10_addon_l10n_br_sale_product-10.0.1.0.0.99.dev24-py3.8-nspkg.pth
odoo/addons/l10n_br_sale_product/README.rst
odoo/addons/l10n_br_sale_product/__init__.py
odoo/addons/l10n_br_sale_product/__manifest__.py
odoo/addons/l10n_br_sale_product/data/l10n_br_sale_product_data.xml
odoo/addons/l10n_br_sale_product/demo/l10n_br_sale_product_demo.xml
odoo/addons/l10n_br_sale_product/demo/product_demo.xml
odoo/addons/l10n_br_sale_product/i18n/l10n_br_sale_product.pot
odoo/addons/l10n_br_sale_product/models/__init__.py
odoo/addons/l10n_br_sale_product/models/res_company.py
odoo/addons/l10n_br_sale_product/models/sale.py
odoo/addons/l10n_br_sale_product/models/sale_line.py
odoo/addons/l10n_br_sale_product/readme/CONFIGURE.rst
odoo/addons/l10n_br_sale_product/readme/CONTRIBUTORS.rst
odoo/addons/l10n_br_sale_product/readme/CREDITS.rst
odoo/addons/l10n_br_sale_product/readme/DESCRIPTION.rst
odoo/addons/l10n_br_sale_product/readme/HISTORY.rst
odoo/addons/l10n_br_sale_product/readme/INSTALL.rst
odoo/addons/l10n_br_sale_product/readme/ROADMAP.rst
odoo/addons/l10n_br_sale_product/readme/USAGE.rst
odoo/addons/l10n_br_sale_product/static/description/icon.png
odoo/addons/l10n_br_sale_product/static/description/index.html
odoo/addons/l10n_br_sale_product/tests/__init__.py
odoo/addons/l10n_br_sale_product/tests/test_l10n_br_sale_product.py
odoo/addons/l10n_br_sale_product/views/res_company_view.xml
odoo/addons/l10n_br_sale_product/views/sale_view.xml
odoo10_addon_l10n_br_sale_product-10.0.1.0.0.99.dev24.dist-info/METADATA
odoo10_addon_l10n_br_sale_product-10.0.1.0.0.99.dev24.dist-info/WHEEL
odoo10_addon_l10n_br_sale_product-10.0.1.0.0.99.dev24.dist-info/namespace_packages.txt
odoo10_addon_l10n_br_sale_product-10.0.1.0.0.99.dev24.dist-info/top_level.txt
odoo10_addon_l10n_br_sale_product-10.0.1.0.0.99.dev24.dist-info/RECORD
